json_x_table/__init__.py
json_x_table/table.py
json_x_table/table_parser.py
json_x_table/text_field.py
json_x_table-0.1.0.dist-info/LICENSE
json_x_table-0.1.0.dist-info/METADATA
json_x_table-0.1.0.dist-info/WHEEL
json_x_table-0.1.0.dist-info/top_level.txt
json_x_table-0.1.0.dist-info/RECORD
